heatdiff/__init__.py
heatdiff/processing/__init__.py
heatdiff/processing/color_segmentation.py
heatdiff/processing/jacobi_segmentation.py
heatdiff/processing/kmeans_segmentation.py
heatdiff/processing/segmentation.py
heatdiff/tests/__init__.py
heatdiff/tests/test_basic.py
heatdiff/tests/test_image_utils.py
heatdiff/tests/test_segmentation.py
heatdiff-0.1.3.dist-info/licenses/LICENSE
heatdiff-0.1.3.dist-info/METADATA
heatdiff-0.1.3.dist-info/WHEEL
heatdiff-0.1.3.dist-info/top_level.txt
heatdiff-0.1.3.dist-info/RECORD
