Metadata-Version: 2.4
Name: heatdiff
Version: 0.1.3
Summary: Image processing using heat equation for segmentation
Author-email: "Jason Ledwidge, Alessio Paesano" <jason.ledwidge@jos-quantum.de>
License: MIT
Project-URL: Homepage, https://github.com/JoSQUANTUM/heatdiff
Classifier: Development Status :: 3 - Alpha
Classifier: Intended Audience :: Science/Research
Classifier: License :: OSI Approved :: MIT License
Classifier: Programming Language :: Python :: 3
Classifier: Topic :: Scientific/Engineering :: Image Processing
Requires-Python: >=3.8
License-File: LICENSE
Requires-Dist: numpy>=1.21.0
Requires-Dist: matplotlib>=3.5.0
Requires-Dist: scipy>=1.7.0
Requires-Dist: scikit-learn>=1.3.2
Requires-Dist: pillow>=10.4.0
Requires-Dist: ipykernel>=6.29.5
Requires-Dist: scikit-image>=0.21.0
Provides-Extra: dev
Requires-Dist: pytest>=8.3.5; extra == "dev"
Requires-Dist: pytest-cov>=5.0.0; extra == "dev"
Requires-Dist: ruff>=0.11.4; extra == "dev"
Dynamic: license-file
